README.rst
setup.py
marshmallow_pynamodb/__init__.py
marshmallow_pynamodb/convert.py
marshmallow_pynamodb/fields.py
marshmallow_pynamodb/schema.py
marshmallow_pynamodb.egg-info/PKG-INFO
marshmallow_pynamodb.egg-info/SOURCES.txt
marshmallow_pynamodb.egg-info/dependency_links.txt
marshmallow_pynamodb.egg-info/requires.txt
marshmallow_pynamodb.egg-info/top_level.txt
test/test_default.py
test/test_field_overriding.py
test/test_fields.py
test/test_integration.py