Metadata-Version: 1.0
Name: marshmallow-pynamodb
Version: 0.8.0
Summary: PynamoDB integration with the marshmallow (de)serialization library
Home-page: UNKNOWN
Author: Mathew Marcus
Author-email: mathewmarcus456@gmail.com
License: UNKNOWN
Platform: UNKNOWN
